kgrid/__init__.py
kgrid/cli.py
kgrid/series.py
kgrid-1.2.0.dist-info/METADATA
kgrid-1.2.0.dist-info/WHEEL
kgrid-1.2.0.dist-info/entry_points.txt
kgrid-1.2.0.dist-info/top_level.txt
kgrid-1.2.0.dist-info/RECORD
