Metadata-Version: 2.1
Name: kgrid
Version: 1.2.0
Summary: Reciprocal space sampling for atomistic crystal structures
Home-page: https://github.com/WMD-group/kgrid
Author: Adam J. Jackson
Author-email: a.j.jackson@physics.org
License: GPL v3
Keywords: chemistry physics k-point sampling reciprocal
Platform: UNKNOWN
Classifier: Development Status :: 3 - Alpha
Classifier: Intended Audience :: Science/Research
Classifier: License :: OSI Approved :: GNU General Public License v3 (GPLv3)
Classifier: Natural Language :: English
Classifier: Programming Language :: Python :: 3.6
Classifier: Topic :: Scientific/Engineering :: Chemistry
Classifier: Topic :: Scientific/Engineering :: Physics
Requires-Python: >=3.6, <4
Requires-Dist: ase (>=3.18)
